mcpl_geant4/__init__.py
mcpl_geant4/cli.py
mcpl_geant4/cmake/MCPLGeant4Config.cmake
mcpl_geant4/cmake/MCPLGeant4ConfigVersion.cmake
mcpl_geant4/cmake/include/MCPLGeant4/G4MCPLGenerator.hh
mcpl_geant4/cmake/include/MCPLGeant4/G4MCPLWriter.hh
mcpl_geant4/cmake/src/G4MCPLGenerator.cc
mcpl_geant4/cmake/src/G4MCPLWriter.cc
mcpl_geant4-0.0.4.dist-info/licenses/LICENSE
mcpl_geant4-0.0.4.dist-info/METADATA
mcpl_geant4-0.0.4.dist-info/WHEEL
mcpl_geant4-0.0.4.dist-info/entry_points.txt
mcpl_geant4-0.0.4.dist-info/top_level.txt
mcpl_geant4-0.0.4.dist-info/RECORD
