Metadata-Version: 2.4
Name: mcpl-geant4
Version: 0.0.4
Summary: Bindings supporting MCPL usage in Geant4.
Author: MCPL developers (Thomas Kittelmann, et. al.)
License:                                  Apache License
Project-URL: Homepage, https://mctools.github.io/mcpl/
Project-URL: Bug Tracker, https://github.com/mctools/mcpl-geant4/issues
Classifier: Programming Language :: Python :: 3
Classifier: License :: OSI Approved :: Apache Software License
License-File: LICENSE
Requires-Dist: mcpl-core>=2.2.0
Dynamic: license-file
